{
  "version": 2,
  "routes": [
    {
      "src": "/",
      "dest": "/simple-login.html"
    },
    {
      "src": "/login",
      "dest": "/simple-login.html"
    },
    {
      "src": "/dashboard",
      "dest": "/dashboard-fixed.html"
    },
    {
      "src": "/students",
      "dest": "/frontend/students-enhanced.html"
    },
    {
      "src": "/courses",
      "dest": "/courses.html"
    },
    {
      "src": "/data-recovery",
      "dest": "/data-recovery.html"
    },
    {
      "src": "/simple-login.html",
      "dest": "/simple-login.html"
    },
    {
      "src": "/dashboard-fixed.html",
      "dest": "/dashboard-fixed.html"
    },
    {
      "src": "/courses.html",
      "dest": "/courses.html"
    },
    {
      "src": "/data-recovery.html",
      "dest": "/data-recovery.html"
    },
    {
      "src": "/frontend/(.*)",
      "dest": "/frontend/$1"
    },
    {
      "src": "/frontend/students-enhanced.html",
      "dest": "/frontend/students-enhanced.html"
    },
    {
      "src": "/frontend/api.js",
      "dest": "/frontend/api.js"
    },
    {
      "src": "/frontend/(.*).js",
      "dest": "/frontend/$1.js"
    },
    {
      "src": "/frontend/(.*).css",
      "dest": "/frontend/$1.css"
    },
    {
      "src": "/(.*)",
      "dest": "/$1"
    }
  ]
}
